Metadata-Version: 1.2
Name: pywinwatcher
Version: 0.0.1
Summary: Operating system event monitoring package
Home-page: https://github.com/drobotun/pywinwatcher
Author: Evgeny Drobotun
Author-email: drobotun@xakep.ru
License: MIT
Project-URL: Source, https://github.com/drobotun/pywinwatcher
Keywords: system event,monitoring,file system event,process event,registry event
Platform: UNKNOWN
Classifier: Environment :: Win32 (MS Windows)
Classifier: Development Status :: 4 - Beta
Classifier: Intended Audience :: Developers
Classifier: Intended Audience :: System Administrators
Classifier: Operating System :: Microsoft :: Windows
Classifier: License :: OSI Approved :: MIT License
Classifier: Programming Language :: Python :: 3.5
Classifier: Programming Language :: Python :: 3.8
